Metadata-Version: 2.4
Name: llama-index-postprocessor-cohere-rerank
Version: 0.5.1
Summary: llama-index postprocessor cohere rerank integration
Author-email: Your Name <you@example.com>
License-Expression: MIT
License-File: LICENSE
Requires-Python: <4.0,>=3.9
Requires-Dist: cohere<6,>=5.1.1
Requires-Dist: llama-index-core<0.15,>=0.13.0
